{
    "demand_fetches": {
        "total": 26140940.35714286,
        "instrn": 0.0,
        "data": 26140940.35714286,
        "read": 24017767.14285714,
        "write": 2123173.214285714,
        "misc": 0.0
    },
    "demand_misses": {
        "total": 3645727.3571428573,
        "instrn": 0.0,
        "data": 3645727.3571428573,
        "read": 3346201.3571428573,
        "write": 299526.0,
        "misc": 0.0
    },
    "demand_miss_rate": {
        "total": 0.12969999999999998,
        "instrn": 0.0,
        "data": 0.12969999999999998,
        "read": 0.12918571428571426,
        "write": 0.13382857142857144,
        "misc": 0.0
    },
    "bytes_from_memory": 116663275.42857143,
    "bytes_to_memory": 10609366.857142856,
    "total_bytes_rw_mem": 127272642.28571428
}